mbf_sampledata/__init__.py
mbf_sampledata/data/mbf_align/broken.fq
mbf_sampledata/data/mbf_align/build_hs22.py
mbf_sampledata/data/mbf_align/chipseq_chr22.bam
mbf_sampledata/data/mbf_align/chipseq_chr22.bam.bai
mbf_sampledata/data/mbf_align/chipseq_chr22_subset.bam
mbf_sampledata/data/mbf_align/chipseq_chr22_subset.bam.bai
mbf_sampledata/data/mbf_align/chipseq_chr22_subset_plus_unmapped.bam
mbf_sampledata/data/mbf_align/chipseq_chr22_subset_plus_unmapped.bam.bai
mbf_sampledata/data/mbf_align/ex1.sam
mbf_sampledata/data/mbf_align/ex2.bam
mbf_sampledata/data/mbf_align/ex2.bam.bai
mbf_sampledata/data/mbf_align/extended_read_test.bam
mbf_sampledata/data/mbf_align/extended_read_test.bam.bai
mbf_sampledata/data/mbf_align/hs_22_genes.msgpack.gz
mbf_sampledata/data/mbf_align/hs_22_transcripts.msgpack.gz
mbf_sampledata/data/mbf_align/paired_end.bam
mbf_sampledata/data/mbf_align/paired_end.bam.bai
mbf_sampledata/data/mbf_align/paired_end2.bam
mbf_sampledata/data/mbf_align/rnaseq_spliced.bam
mbf_sampledata/data/mbf_align/rnaseq_spliced.bam.bai
mbf_sampledata/data/mbf_align/rnaseq_spliced_chr22.bam
mbf_sampledata/data/mbf_align/rnaseq_spliced_chr22.bam.bai
mbf_sampledata/data/mbf_align/size.raw
mbf_sampledata/data/mbf_align/size.raw._wrong_name.tar
mbf_sampledata/data/mbf_align/size.raw.bz2
mbf_sampledata/data/mbf_align/size.raw.gz
mbf_sampledata/data/mbf_align/size.raw.tar
mbf_sampledata/data/mbf_align/size.raw.tar.bz2
mbf_sampledata/data/mbf_align/size.raw.tgz
mbf_sampledata/data/mbf_align/size.raw.with_csv.tar
mbf_sampledata/data/mbf_align/size.raw.zip
mbf_sampledata/data/mbf_align/test2.fastq.gz
mbf_sampledata/data/mbf_align/sample_a/a.fastq
mbf_sampledata/data/mbf_align/sample_a/b.fastq.gz
mbf_sampledata/data/mbf_align/sample_a/not_a_fastq_is_it.txt
mbf_sampledata/data/mbf_align/sample_b/a_R1_.fastq.gz
mbf_sampledata/data/mbf_align/sample_b/a_R2_.fastq.gz
mbf_sampledata/data/mbf_align/sample_b/not_a_fastq_is_it.txt
mbf_sampledata/data/mbf_align/sample_c/a_R2_.fastq.gz
mbf_sampledata-0.2.dist-info/AUTHORS.rst
mbf_sampledata-0.2.dist-info/LICENSE.txt
mbf_sampledata-0.2.dist-info/METADATA
mbf_sampledata-0.2.dist-info/WHEEL
mbf_sampledata-0.2.dist-info/top_level.txt
mbf_sampledata-0.2.dist-info/RECORD
